pyjan26/__init__.py
pyjan26/core.py
pyjan26/main.py
pyjan26/registry.py
pyjan26/project_structure/__init__.py
pyjan26/project_structure/settings.py
pyjan26/project_structure/_content/index.md
pyjan26/project_structure/_templates/base.html
pyjan26-0.14.dist-info/LICENSE
pyjan26-0.14.dist-info/METADATA
pyjan26-0.14.dist-info/WHEEL
pyjan26-0.14.dist-info/top_level.txt
pyjan26-0.14.dist-info/RECORD
