Metadata-Version: 2.1
Name: pyjan26
Version: 0.14
Summary: PyJan26 is a static site generator written in Python. It allows you to generate static websites from templates and content files, with support for pagination, & extendable using plugins
Home-page: UNKNOWN
Author: Josnin
License: MIT
Project-URL: Source, https://github.com/josnin/pyjan26
Platform: UNKNOWN
Requires-Python: >=3.10
License-File: LICENSE
Requires-Dist: Jinja2>=3.1.4
Requires-Dist: python-frontmatter==1.1.0
